CHANGELOG
COPYRIGHT
LICENSE
MANIFEST.in
README.rst
setup.py
./__init__.py
./country.py
./country.xml
./party.py
./party.xml
./tryton.cfg
./scripts/__init__.py
./scripts/import_postal_codes_locations.py
./tests/__init__.py
./tests/scenario_party_address_location.rst
./tests/test_module.py
./tests/test_scenario.py
./view/address_distance_list.xml
./view/address_form.xml
./view/postal_code_form.xml
doc/conf.py
doc/configuration.rst
doc/design.rst
doc/index.rst
doc/installation.rst
doc/license.rst
doc/reference.rst
doc/setup.rst
doc/support.rst
trytonlq_party_address_location.egg-info/PKG-INFO
trytonlq_party_address_location.egg-info/SOURCES.txt
trytonlq_party_address_location.egg-info/dependency_links.txt
trytonlq_party_address_location.egg-info/entry_points.txt
trytonlq_party_address_location.egg-info/not-zip-safe
trytonlq_party_address_location.egg-info/requires.txt
trytonlq_party_address_location.egg-info/top_level.txt