Metadata-Version: 2.1
Name: trytonlq-party-address-location
Version: 7.0.0
Summary: Tryton module that adds a latitude and longitude to addresses
Home-page: https://foss.heptapod.net/libateq/tryton-modules
Author: David Harper
Author-email: tryton@libateq.org
License: GPL-3
Project-URL: Bug Tracker, https://foss.heptapod.net/libateq/tryton-modules/-/issues
Project-URL: Source Code, https://foss.heptapod.net/libateq/tryton-modules
Keywords: tryton party address location
Platform: UNKNOWN
Classifier: Development Status :: 5 - Production/Stable
Classifier: Environment :: Plugins
Classifier: Framework :: Tryton
Classifier: Intended Audience :: Developers
Classifier: Intended Audience :: Financial and Insurance Industry
Classifier: Intended Audience :: Legal Industry
Classifier: License :: OSI Approved :: GNU General Public License v3 or later (GPLv3+)
Classifier: Natural Language :: English
Classifier: Operating System :: OS Independent
Classifier: Programming Language :: Python :: 3
Classifier: Programming Language :: Python :: 3.7
Classifier: Programming Language :: Python :: 3.8
Classifier: Programming Language :: Python :: 3.9
Classifier: Programming Language :: Python :: 3.10
Classifier: Programming Language :: Python :: Implementation :: CPython
Classifier: Topic :: Office/Business
Requires-Python: >=3.7
Provides-Extra: test
